{
  "version": "0.0.1",
  "default_environment": "testing",
  "logging": {
    "additional_info": {
      "category": "sdk",
      "integration_type": "php"
    },
    "file": {
      "enabled": false,
      "relative_path": "logs/ns8.log",
      "log_level": "Error"
    },
    "api": {
      "enabled": true,
      "log_level": "Info"
    },
    "record_all_http_calls": true
  },
  "production": {
    "authorization": {
      "access_token": "",
      "auth_user": ""
    }
  },
  "testing": {
    "authorization": {
      "access_token": "",
      "auth_user": ""
    }
  },
  "development": {
    "authorization": {
      "access_token": "",
      "auth_user": ""
    },
    "urls": {
      "client_url": "https://test-protect-client.ns8.com",
      "api_url": "https://test-protect.ns8.com"
    }
  }
}
